setup.py
txmarconi/__init__.py
txmarconi/client.py
txmarconi/version.py
txmarconi.egg-info/PKG-INFO
txmarconi.egg-info/SOURCES.txt
txmarconi.egg-info/dependency_links.txt
txmarconi.egg-info/requires.txt
txmarconi.egg-info/top_level.txt