Metadata-Version: 1.0
Name: txmarconi
Version: 0.1-2
Summary: A Twisted client for OpenStack Marconi: https://wiki.openstack.org/wiki/Marconi
Home-page: https://github.com/russellhaering/txmarconi
Author: Russell Haering
Author-email: russellhaering@gmail.com
License: Apache License (2.0)
Platform: UNKNOWN
